{
  "imports": {
    "@frontside-graphgen/types": "../graphql/types.ts",
    "@mui/material/": "https://esm.sh/@mui/material@5.10.6/",
    "@mui/lab/": "https://esm.sh/@mui/lab@5.0.0-alpha.100/",
    "@mui/icons-material/": "https://esm.sh/@mui/icons-material@5.10.6/",
    "immer": "https://esm.sh/immer@9.0.15",
    "react": "https://esm.sh/react@18.2.0",
    "react/": "https://esm.sh/react@18.2.0/",
    "react-dom": "https://esm.sh/react-dom@18.2.0",
    "react-dom/": "https://esm.sh/react-dom@18.2.0/",
    "ts-pattern": "https://esm.sh/ts-pattern@4.0.5"
  }
}
